<?xml version="1.0" encoding="UTF-8"?>
<databaseChangeLog
    xmlns="http://www.liquibase.org/xml/ns/dbchangelog"
    xmlns:xsi="http://www.w3.org/2001/XMLSchema-instance"
    xsi:schemaLocation="http://www.liquibase.org/xml/ns/dbchangelog
    http://www.liquibase.org/xml/ns/dbchangelog/dbchangelog-4.20.xsd">

    <changeSet id="007-create-gedcom-event-participants" author="system">
        <createTable tableName="gedcom_event_participants">
            <column name="id" type="BIGINT" autoIncrement="true">
                <constraints primaryKey="true" nullable="false"/>
            </column>
            <column name="event_id" type="BIGINT">
                <constraints nullable="false"/>
            </column>
            <column name="individual_id" type="VARCHAR(20)">
                <constraints nullable="false"/>
            </column>
            <column name="role" type="VARCHAR(20)">
                <constraints nullable="false"/>
            </column>
        </createTable>

        <createIndex tableName="gedcom_event_participants" indexName="idx_eventparticipant_event">
            <column name="event_id"/>
        </createIndex>

        <createIndex tableName="gedcom_event_participants" indexName="idx_eventparticipant_individual">
            <column name="individual_id"/>
        </createIndex>
    </changeSet>

</databaseChangeLog>
